[
    {
        "nid": "TangledUpInBlue",
        "name": "Tangled Up In Blue",
        "desc": "Unit becomes more powerful, heavier, and less mobile over time.",
        "icon_nid": "Skills",
        "icon_index": [
            0,
            0
        ],
        "components": [
            [
                "condition",
                "game.turncount != 1"
            ],
            [
                "event_on_upkeep",
                "Global Ability_GainTangledUpInBlueStack"
            ],
            [
                "class_skill",
                null
            ]
        ]
    }
]