[
    {
        "nid": "Church",
        "name": "Church",
        "desc": "Hector only. Effective against dragons",
        "icon_nid": "{2WB} (Icon Blitz 1) Brave Axe",
        "icon_index": [
            0,
            0
        ],
        "components": [
            [
                "weapon",
                null
            ],
            [
                "value",
                2200
            ],
            [
                "target_enemy",
                null
            ],
            [
                "min_range",
                1
            ],
            [
                "max_range",
                1
            ],
            [
                "damage",
                22
            ],
            [
                "hit",
                85
            ],
            [
                "crit",
                4
            ],
            [
                "weight",
                16
            ],
            [
                "uses",
                60
            ],
            [
                "uses_options",
                {
                    "lose_uses_on_miss": false,
                    "one_loss_per_combat": false
                }
            ],
            [
                "level_exp",
                null
            ],
            [
                "weapon_type",
                "Axe"
            ],
            [
                "weapon_rank",
                "S"
            ],
            [
                "stat_change",
                [
                    [
                        "STR",
                        5
                    ],
                    [
                        "SKL",
                        5
                    ],
                    [
                        "SPD",
                        5
                    ],
                    [
                        "DEF",
                        5
                    ],
                    [
                        "RES",
                        5
                    ],
                    [
                        "LCK",
                        5
                    ]
                ]
            ],
            [
                "prf_unit",
                [
                    "Hector"
                ]
            ],
            [
                "effective_damage",
                {
                    "effective_tags": [
                        "Dragon"
                    ],
                    "effective_multiplier": 4.0,
                    "effective_bonus_damage": 0,
                    "show_effectiveness_flash": true,
                    "weapon_effectiveness_multiplied": true
                }
            ]
        ]
    }
]