[
    {
        "nid": "MoneyRing",
        "name": "Money Ring",
        "desc": "Grants a skill, where the unit gets money from hitting enemies. ",
        "icon_nid": "Skills",
        "icon_index": [
            0,
            0
        ],
        "components": [
            [
                "status_on_equip",
                "MoneyRing"
            ],
            [
                "equippable_accessory",
                null
            ],
            [
                "value",
                20000
            ]
        ]
    }
]