[
    {
        "nid": "41",
        "name": "Chapter 41: The Berserker",
        "tilemap": "30H",
        "bg_tilemap": null,
        "party": "Eliwoods",
        "music": {
            "player_phase": "LaCaution",
            "player_battle": "LaCaution",
            "enemy_phase": "LaCaution",
            "enemy_battle": "LaCaution",
            "boss_battle": "LaCaution"
        },
        "objective": {
            "simple": "Seize tile",
            "win": "",
            "loss": ""
        },
        "roam": false,
        "roam_unit": null,
        "go_to_overworld": false,
        "should_record": true,
        "tags": [],
        "units": [
            {
                "nid": "Hector",
                "team": "player",
                "ai": "None",
                "roam_ai": null,
                "ai_group": "",
                "starting_position": [
                    25,
                    13
                ],
                "starting_traveler": null,
                "generic": false
            },
            {
                "nid": "111",
                "variant": null,
                "level": 12,
                "klass": "Knight",
                "faction": "Soldier",
                "starting_items": [
                    [
                        "Steel_Lance",
                        false
                    ]
                ],
                "starting_skills": [],
                "team": "enemy",
                "ai": "Pursue",
                "roam_ai": null,
                "ai_group": "",
                "starting_position": [
                    12,
                    12
                ],
                "starting_traveler": null,
                "generic": true
            },
            {
                "nid": "115",
                "variant": null,
                "level": 12,
                "klass": "Knight",
                "faction": "Soldier",
                "starting_items": [
                    [
                        "Steel_Lance",
                        false
                    ]
                ],
                "starting_skills": [],
                "team": "enemy",
                "ai": "Pursue",
                "roam_ai": null,
                "ai_group": "",
                "starting_position": [
                    11,
                    13
                ],
                "starting_traveler": null,
                "generic": true
            },
            {
                "nid": "116",
                "variant": null,
                "level": 12,
                "klass": "Knight",
                "faction": "Soldier",
                "starting_items": [
                    [
                        "Javelin",
                        false
                    ]
                ],
                "starting_skills": [],
                "team": "enemy",
                "ai": "Pursue",
                "roam_ai": null,
                "ai_group": "",
                "starting_position": [
                    17,
                    11
                ],
                "starting_traveler": null,
                "generic": true
            },
            {
                "nid": "117",
                "variant": null,
                "level": 12,
                "klass": "Knight",
                "faction": "Soldier",
                "starting_items": [
                    [
                        "Iron_Sword",
                        false
                    ]
                ],
                "starting_skills": [],
                "team": "enemy",
                "ai": "Pursue",
                "roam_ai": null,
                "ai_group": "",
                "starting_position": [
                    23,
                    9
                ],
                "starting_traveler": null,
                "generic": true
            },
            {
                "nid": "118",
                "variant": null,
                "level": 12,
                "klass": "Knight",
                "faction": "Soldier",
                "starting_items": [
                    [
                        "Axereaver",
                        false
                    ]
                ],
                "starting_skills": [],
                "team": "enemy",
                "ai": "Pursue",
                "roam_ai": null,
                "ai_group": "",
                "starting_position": [
                    28,
                    9
                ],
                "starting_traveler": null,
                "generic": true
            },
            {
                "nid": "124",
                "variant": null,
                "level": 12,
                "klass": "Knight",
                "faction": "Soldier",
                "starting_items": [
                    [
                        "Heavy_Spear",
                        false
                    ]
                ],
                "starting_skills": [],
                "team": "enemy",
                "ai": "Pursue",
                "roam_ai": null,
                "ai_group": "",
                "starting_position": [
                    12,
                    4
                ],
                "starting_traveler": null,
                "generic": true
            },
            {
                "nid": "125",
                "variant": null,
                "level": 12,
                "klass": "Knight",
                "faction": "Soldier",
                "starting_items": [
                    [
                        "Horseslayer",
                        false
                    ]
                ],
                "starting_skills": [],
                "team": "enemy",
                "ai": "Pursue",
                "roam_ai": null,
                "ai_group": "",
                "starting_position": [
                    10,
                    1
                ],
                "starting_traveler": null,
                "generic": true
            },
            {
                "nid": "119",
                "variant": null,
                "level": 12,
                "klass": "Knight",
                "faction": "Soldier",
                "starting_items": [
                    [
                        "Killer_Lance",
                        false
                    ]
                ],
                "starting_skills": [],
                "team": "enemy",
                "ai": "Pursue",
                "roam_ai": null,
                "ai_group": "",
                "starting_position": [
                    21,
                    6
                ],
                "starting_traveler": null,
                "generic": true
            },
            {
                "nid": "130",
                "variant": null,
                "level": 12,
                "klass": "Knight",
                "faction": "Soldier",
                "starting_items": [
                    [
                        "Silver_Lance",
                        false
                    ]
                ],
                "starting_skills": [],
                "team": "enemy",
                "ai": "Pursue",
                "roam_ai": null,
                "ai_group": "",
                "starting_position": [
                    4,
                    10
                ],
                "starting_traveler": null,
                "generic": true
            },
            {
                "nid": "121",
                "variant": null,
                "level": 12,
                "klass": "Knight",
                "faction": "Soldier",
                "starting_items": [
                    [
                        "Killer_Lance",
                        false
                    ]
                ],
                "starting_skills": [],
                "team": "enemy",
                "ai": "Pursue",
                "roam_ai": null,
                "ai_group": "",
                "starting_position": [
                    21,
                    1
                ],
                "starting_traveler": null,
                "generic": true
            },
            {
                "nid": "112",
                "variant": null,
                "level": 12,
                "klass": "Mage",
                "faction": "Soldier",
                "starting_items": [
                    [
                        "Thunder",
                        false
                    ]
                ],
                "starting_skills": [],
                "team": "enemy",
                "ai": "Pursue",
                "roam_ai": null,
                "ai_group": "",
                "starting_position": [
                    26,
                    1
                ],
                "starting_traveler": null,
                "generic": true
            },
            {
                "nid": "123",
                "variant": null,
                "level": 9,
                "klass": "Mage",
                "faction": "Soldier",
                "starting_items": [
                    [
                        "Elfire",
                        false
                    ]
                ],
                "starting_skills": [],
                "team": "enemy",
                "ai": "Pursue",
                "roam_ai": null,
                "ai_group": "",
                "starting_position": [
                    16,
                    5
                ],
                "starting_traveler": null,
                "generic": true
            },
            {
                "nid": "127",
                "variant": null,
                "level": 9,
                "klass": "Mage",
                "faction": "Soldier",
                "starting_items": [
                    [
                        "Thunder",
                        false
                    ]
                ],
                "starting_skills": [],
                "team": "enemy",
                "ai": "Guard",
                "roam_ai": null,
                "ai_group": "",
                "starting_position": [
                    5,
                    2
                ],
                "starting_traveler": null,
                "generic": true
            },
            {
                "nid": "128",
                "variant": null,
                "level": 9,
                "klass": "Mage",
                "faction": "Soldier",
                "starting_items": [
                    [
                        "Elfire",
                        false
                    ]
                ],
                "starting_skills": [],
                "team": "enemy",
                "ai": "Guard",
                "roam_ai": null,
                "ai_group": "",
                "starting_position": [
                    3,
                    2
                ],
                "starting_traveler": null,
                "generic": true
            },
            {
                "nid": "129",
                "variant": null,
                "level": 9,
                "klass": "Mage",
                "faction": "Soldier",
                "starting_items": [
                    [
                        "Fimbulvetr",
                        false
                    ]
                ],
                "starting_skills": [],
                "team": "enemy",
                "ai": "Pursue",
                "roam_ai": null,
                "ai_group": "",
                "starting_position": [
                    4,
                    8
                ],
                "starting_traveler": null,
                "generic": true
            },
            {
                "nid": "131",
                "variant": null,
                "level": 9,
                "klass": "Mage",
                "faction": "Soldier",
                "starting_items": [
                    [
                        "Elfire",
                        false
                    ]
                ],
                "starting_skills": [],
                "team": "enemy",
                "ai": "Pursue",
                "roam_ai": null,
                "ai_group": "",
                "starting_position": [
                    5,
                    13
                ],
                "starting_traveler": null,
                "generic": true
            },
            {
                "nid": "113",
                "variant": null,
                "level": 20,
                "klass": "Thief",
                "faction": "Soldier",
                "starting_items": [
                    [
                        "Iron_Sword",
                        false
                    ],
                    [
                        "Lockpick",
                        false
                    ]
                ],
                "starting_skills": [],
                "team": "enemy",
                "ai": "Thief",
                "roam_ai": null,
                "ai_group": "",
                "starting_position": [
                    29,
                    12
                ],
                "starting_traveler": null,
                "generic": true
            },
            {
                "nid": "122",
                "variant": null,
                "level": 20,
                "klass": "Thief",
                "faction": "Soldier",
                "starting_items": [
                    [
                        "Killing_Edge",
                        false
                    ],
                    [
                        "Lockpick",
                        false
                    ]
                ],
                "starting_skills": [],
                "team": "enemy",
                "ai": "Thief",
                "roam_ai": null,
                "ai_group": "",
                "starting_position": [
                    13,
                    6
                ],
                "starting_traveler": null,
                "generic": true
            },
            {
                "nid": "120",
                "variant": null,
                "level": 20,
                "klass": "Thief",
                "faction": "Soldier",
                "starting_items": [
                    [
                        "Armorslayer",
                        false
                    ],
                    [
                        "Lockpick",
                        false
                    ]
                ],
                "starting_skills": [],
                "team": "enemy",
                "ai": "Thief",
                "roam_ai": null,
                "ai_group": "",
                "starting_position": [
                    23,
                    5
                ],
                "starting_traveler": null,
                "generic": true
            },
            {
                "nid": "114",
                "variant": null,
                "level": 12,
                "klass": "Fighter",
                "faction": "Soldier",
                "starting_items": [
                    [
                        "Swordreaver",
                        false
                    ]
                ],
                "starting_skills": [],
                "team": "enemy",
                "ai": "Pursue",
                "roam_ai": null,
                "ai_group": "",
                "starting_position": [
                    12,
                    0
                ],
                "starting_traveler": null,
                "generic": true
            },
            {
                "nid": "126",
                "variant": null,
                "level": 12,
                "klass": "Fighter",
                "faction": "Soldier",
                "starting_items": [
                    [
                        "Iron_Sword",
                        false
                    ]
                ],
                "starting_skills": [],
                "team": "enemy",
                "ai": "None",
                "roam_ai": null,
                "ai_group": "",
                "starting_position": null,
                "starting_traveler": null,
                "generic": true
            },
            {
                "nid": "Kaim",
                "team": "enemy",
                "ai": "Guard",
                "roam_ai": null,
                "ai_group": "",
                "starting_position": [
                    4,
                    1
                ],
                "starting_traveler": null,
                "generic": false
            },
            {
                "nid": "132",
                "variant": null,
                "level": 12,
                "klass": "Mercenary",
                "faction": "Soldier",
                "starting_items": [
                    [
                        "Armorslayer",
                        false
                    ]
                ],
                "starting_skills": [],
                "team": "enemy",
                "ai": "Guard",
                "roam_ai": null,
                "ai_group": "",
                "starting_position": [
                    9,
                    3
                ],
                "starting_traveler": null,
                "generic": true
            }
        ],
        "regions": [
            {
                "nid": "New Region",
                "region_type": "formation",
                "position": [
                    26,
                    14
                ],
                "size": [
                    1,
                    1
                ],
                "sub_nid": "",
                "condition": "True",
                "time_left": null,
                "only_once": false,
                "interrupt_move": false
            },
            {
                "nid": "seezeed",
                "region_type": "event",
                "position": [
                    4,
                    1
                ],
                "size": [
                    1,
                    1
                ],
                "sub_nid": "Seize",
                "condition": "unit.nid == 'Hector'",
                "time_left": null,
                "only_once": false,
                "interrupt_move": false
            },
            {
                "nid": "Chest1",
                "region_type": "event",
                "position": [
                    28,
                    1
                ],
                "size": [
                    1,
                    1
                ],
                "sub_nid": "Chest",
                "condition": "unit.can_unlock(region)",
                "time_left": null,
                "only_once": true,
                "interrupt_move": false
            },
            {
                "nid": "Chest2",
                "region_type": "event",
                "position": [
                    16,
                    15
                ],
                "size": [
                    1,
                    1
                ],
                "sub_nid": "Chest",
                "condition": "unit.can_unlock(region)",
                "time_left": null,
                "only_once": true,
                "interrupt_move": false
            },
            {
                "nid": "Chest3",
                "region_type": "event",
                "position": [
                    4,
                    12
                ],
                "size": [
                    1,
                    1
                ],
                "sub_nid": "Chest",
                "condition": "unit.can_unlock(region)",
                "time_left": null,
                "only_once": true,
                "interrupt_move": false
            },
            {
                "nid": "ThiefEscape",
                "region_type": "event",
                "position": [
                    29,
                    0
                ],
                "size": [
                    1,
                    1
                ],
                "sub_nid": "ThiefEscape",
                "condition": "unit.team == 'enemy'",
                "time_left": null,
                "only_once": false,
                "interrupt_move": false
            }
        ],
        "unit_groups": [],
        "ai_groups": []
    }
]