[
    {
        "name": "Ability_SkyDropStart",
        "trigger": null,
        "level_nid": null,
        "condition": "True",
        "commands": [],
        "only_once": false,
        "priority": 20,
        "_source": [
            "level_var;sd_pos_unit;unit.position",
            "level_var;sd_pos_target;unit2.position",
            "level_var;sd_unit;unit.nid",
            "level_var;sd_target;unit2.nid",
            "level_var;sd_turn;game.turncount",
            "remove_unit;{unit};swoosh",
            "remove_unit;{unit2};swoosh",
            ""
        ],
        "nid": "Global Ability_SkyDropStart"
    }
]